{
  "@context": "https://linked.art/ns/v1/linked-art.json",
  "id": "https://example.org/cdkg/VisualItem/presentation/22",
  "type": "VisualItem",
  "_label": "Visual content of \"RDF Leveled the Advantages of LPG and Keeps 3 Key Benefits: Standards, Semantics & Interoperability\"",
  "created_by": {
    "id": "https://example.org/cdkg/Creation/presentation/22",
    "type": "Creation",
    "caused_by": [
      {
        "id": "https://example.org/cdkg/Activity/presentation/22",
        "type": "Activity",
        "_label": "Presentation of \"RDF Leveled the Advantages of LPG and Keeps 3 Key Benefits: Standards, Semantics & Interoperability\""
      }
    ]
  },
  "digitally_shown_by": [
    {
      "id": "https://example.org/cdkg/DigitalObject/recording/22",
      "type": "DigitalObject",
      "_label": "Recording of \"RDF Leveled the Advantages of LPG and Keeps 3 Key Benefits: Standards, Semantics & Interoperability\""
    }
  ]
}